brom_spades
