Metadata-Version: 1.0
Name: brom-spades
Version: 4.0.2
Summary: Scoring agent for Spades
Home-page: https://gitlab.com/ralphembree/brom-spades
Author: Ralph Embree
Author-email: ralph.embree@brominator.org
License: UNKNOWN
Keywords: brom-spades spades score scoring
Platform: UNKNOWN
